tuyamqtt/__init__.py
tuyamqtt/configure.py
tuyamqtt/device.py
tuyamqtt/database/__init__.py
tuyamqtt-1.1.6.data/data/etc/tuyamqtt.conf
tuyamqtt-1.1.6.data/data/etc/tuyamqtt.service
tuyamqtt-1.1.6.data/scripts/tuyamqtt
tuyamqtt-1.1.6.dist-info/LICENSE
tuyamqtt-1.1.6.dist-info/METADATA
tuyamqtt-1.1.6.dist-info/WHEEL
tuyamqtt-1.1.6.dist-info/top_level.txt
tuyamqtt-1.1.6.dist-info/RECORD
