Metadata-Version: 2.1
Name: tuyamqtt
Version: 1.1.6
Summary: Python middleware for Tuya WiFi smart devices to MQTT
Home-page: https://github.com/TradeFace/tuyamqtt/
Author: tradeface
Author-email: 
License: Unlicense
Keywords: home automation,mqtt,auto discovery,tuya
Platform: any
Classifier: Development Status :: 4 - Beta
Classifier: Intended Audience :: Developers
Classifier: Topic :: Home Automation
Classifier: License :: Public Domain
Classifier: Programming Language :: Python
Classifier: Programming Language :: Python :: 2
Classifier: Programming Language :: Python :: 3
Classifier: Programming Language :: Python :: 3.6
Classifier: Topic :: Home Automation
Requires-Python: >=3.6
Requires-Dist: paho-mqtt (==1.5.0)
Requires-Dist: tuyaface (==1.3.1)
